LICENSE
MANIFEST.in
README.rst
setup.py
django_modeltools.egg-info/PKG-INFO
django_modeltools.egg-info/SOURCES.txt
django_modeltools.egg-info/dependency_links.txt
django_modeltools.egg-info/not-zip-safe
django_modeltools.egg-info/top_level.txt
modeltools/__init__.py
modeltools/enums.py
modeltools/filenames.py
modeltools/managers.py