Metadata-Version: 1.0
Name: django-modeltools
Version: 1.0.1
Summary: A collection of utilities that make dealing with Django models more fun.
Home-page: https://github.com/hzdg/django-modeltools
Author: HZDG
Author-email: webmaster@hzdg.com
License: MIT
Platform: UNKNOWN
Classifier: Environment :: Web Environment
Classifier: Framework :: Django
Classifier: Intended Audience :: Developers
Classifier: Operating System :: OS Independent
Classifier: Programming Language :: Python
Classifier: Topic :: Internet :: WWW/HTTP
